watertap_contrib/reflo/__init__.py
watertap_contrib/reflo/_version.py
watertap_contrib/reflo/conftest.py
watertap_contrib/reflo/core/__init__.py
watertap_contrib/reflo/core/pysam_watertap.py
watertap_contrib/reflo/core/solar_energy_base.py
watertap_contrib/reflo/core/wt_reflo_database.py
watertap_contrib/reflo/core/tests/test_pysam_watertap.py
watertap_contrib/reflo/core/tests/test_reflo_wt_database.py
watertap_contrib/reflo/costing/__init__.py
watertap_contrib/reflo/costing/util.py
watertap_contrib/reflo/costing/watertap_reflo_costing_package.py
watertap_contrib/reflo/costing/solar/__init__.py
watertap_contrib/reflo/costing/solar/flat_plate.py
watertap_contrib/reflo/costing/solar/pv.py
watertap_contrib/reflo/costing/solar/pv_battery.py
watertap_contrib/reflo/costing/solar/thermal_energy_storage.py
watertap_contrib/reflo/costing/solar/trough_surrogate.py
watertap_contrib/reflo/costing/tests/dummy_costing_units.py
watertap_contrib/reflo/costing/tests/test_reflo_watertap_costing_package.py
watertap_contrib/reflo/costing/units/__init__.py
watertap_contrib/reflo/costing/units/air_stripping.py
watertap_contrib/reflo/costing/units/chemical_softening.py
watertap_contrib/reflo/costing/units/deep_well_injection.py
watertap_contrib/reflo/costing/units/evaporation_pond.py
watertap_contrib/reflo/costing/units/forward_osmosis_zo.py
watertap_contrib/reflo/costing/units/lt_med_surrogate.py
watertap_contrib/reflo/costing/units/med_tvc_surrogate.py
watertap_contrib/reflo/costing/units/multi_effect_crystallizer.py
watertap_contrib/reflo/costing/units/solar_still.py
watertap_contrib/reflo/costing/units/vagmd_surrogate.py
watertap_contrib/reflo/costing/units/waiv.py
watertap_contrib/reflo/data/__init__.py
watertap_contrib/reflo/data/technoeconomic/component_list.yaml
watertap_contrib/reflo/data/technoeconomic/electrocoagulation.yaml
watertap_contrib/reflo/data/technoeconomic/kbhdp_case_study.yaml
watertap_contrib/reflo/data/technoeconomic/reflo.yaml
watertap_reflo-0.21.dist-info/licenses/LICENSE
watertap_reflo-0.21.dist-info/METADATA
watertap_reflo-0.21.dist-info/WHEEL
watertap_reflo-0.21.dist-info/top_level.txt
watertap_reflo-0.21.dist-info/RECORD
