Metadata-Version: 2.4
Name: watertap-reflo
Version: 0.21
Author: WaterTAP-REFLO contributors
Requires-Python: >=3.9
License-File: LICENSE
Requires-Dist: watertap==1.4.0
Requires-Dist: idaes_pse==2.8.0
Requires-Dist: pyomo<6.9.3,>=6.6.1
Requires-Dist: nrel-pysam>=7.0.0
Requires-Dist: pint<0.25
Requires-Dist: requests>=2.32
Provides-Extra: dev
Requires-Dist: nbsphinx; extra == "dev"
Requires-Dist: jinja2<3.1.0; extra == "dev"
Requires-Dist: Sphinx; extra == "dev"
Requires-Dist: sphinx_rtd_theme>=0.30; extra == "dev"
Dynamic: author
Dynamic: license-file
Dynamic: provides-extra
Dynamic: requires-dist
Dynamic: requires-python
